setup.py
albertai/__init__.py
albertai/embedchain.py
albertai/utils.py
albertai.egg-info/PKG-INFO
albertai.egg-info/SOURCES.txt
albertai.egg-info/dependency_links.txt
albertai.egg-info/requires.txt
albertai.egg-info/top_level.txt
albertai/apps/App.py
albertai/apps/CustomApp.py
albertai/apps/Llama2App.py
albertai/apps/OpenSourceApp.py
albertai/apps/PersonApp.py
albertai/apps/__init__.py
albertai/bots/__init__.py
albertai/bots/base.py
albertai/bots/whatsapp.py
albertai/chunkers/__init__.py
albertai/chunkers/base_chunker.py
albertai/chunkers/csv.py
albertai/chunkers/docs_site.py
albertai/chunkers/docx_file.py
albertai/chunkers/notion.py
albertai/chunkers/pdf_file.py
albertai/chunkers/qna_pair.py
albertai/chunkers/text.py
albertai/chunkers/web_page.py
albertai/chunkers/youtube_video.py
albertai/config/AddConfig.py
albertai/config/BaseConfig.py
albertai/config/ChatConfig.py
albertai/config/QueryConfig.py
albertai/config/__init__.py
albertai/config/apps/AppConfig.py
albertai/config/apps/BaseAppConfig.py
albertai/config/apps/CustomAppConfig.py
albertai/config/apps/OpenSourceAppConfig.py
albertai/config/apps/__init__.py
albertai/config/vectordbs/ElasticsearchDBConfig.py
albertai/config/vectordbs/__init__.py
albertai/data_formatter/__init__.py
albertai/data_formatter/data_formatter.py
albertai/loaders/__init__.py
albertai/loaders/base_loader.py
albertai/loaders/csv.py
albertai/loaders/docs_site_loader.py
albertai/loaders/docx_file.py
albertai/loaders/local_qna_pair.py
albertai/loaders/local_text.py
albertai/loaders/notion.py
albertai/loaders/pdf_file.py
albertai/loaders/sitemap.py
albertai/loaders/web_page.py
albertai/loaders/youtube_video.py
albertai/models/EmbeddingFunctions.py
albertai/models/Providers.py
albertai/models/VectorDatabases.py
albertai/models/VectorDimensions.py
albertai/models/__init__.py
albertai/models/data_type.py
albertai/vectordb/__init__.py
albertai/vectordb/base_vector_db.py
albertai/vectordb/chroma_db.py
albertai/vectordb/elasticsearch_db.py