Metadata-Version: 2.1
Name: albertai
Version: 0.0.5
Summary: A modified version of Embedchain.
Home-page: https://github.com/embedchain/embedchain
Author: Professor
Author-email: your.email@domain.com
